{
  "list": [
    {
      "name": "boom-palm",
      "productType": "natuur"
    },
    {
      "name": "boom-standaard",
      "productType": "natuur"
    },
    {
      "name": "boom-super",
      "productType": "natuur"
    },
    {
      "name": "bank-modern",
      "productType": "uitrusting"
    },
    {
      "name": "vuilbak",
      "productType": "uitrusting"
    },
    {
      "name": "buiten-tafel",
      "productType": "uitrusting"
    },
    {
      "name": "buiten-tafel-2",
      "productType": "uitrusting"
    },
    {
      "name": "buiten-bank",
      "productType": "uitrusting"
    },
    {
      "name": "water-paal",
      "productType": "water"
    },
    {
      "name": "fontein",
      "productType": "water"
    },
    {
      "name": "licht-modern",
      "productType": "licht"
    },
    {
      "name": "licht-park",
      "productType": "licht"
    }
  ]
}